ibm_common_scoring_utils/__init__.py
ibm_common_scoring_utils/clients/__init__.py
ibm_common_scoring_utils/clients/aws_provider.py
ibm_common_scoring_utils/clients/azure_service_provider.py
ibm_common_scoring_utils/clients/azure_studio_provider.py
ibm_common_scoring_utils/clients/custom_ml_provider.py
ibm_common_scoring_utils/clients/service_provider.py
ibm_common_scoring_utils/clients/spss_provider.py
ibm_common_scoring_utils/clients/wml_provider.py
ibm_common_scoring_utils/common/__init__.py
ibm_common_scoring_utils/common/configuration.py
ibm_common_scoring_utils/common/score_factory.py
ibm_common_scoring_utils/core/__init__.py
ibm_common_scoring_utils/core/score_manager.py
ibm_common_scoring_utils/core/executors/__init__.py
ibm_common_scoring_utils/core/executors/asyncio_executor.py
ibm_common_scoring_utils/utils/__init__.py
ibm_common_scoring_utils/utils/auth_utils.py
ibm_common_scoring_utils/utils/constants.py
ibm_common_scoring_utils/utils/data_time_util.py
ibm_common_scoring_utils/utils/lru_cache.py
ibm_common_scoring_utils/utils/python_utils.py
ibm_common_scoring_utils/utils/rest_util.py
ibm_common_scoring_utils/utils/scoring_utils_logger.py
ibm_common_scoring_utils/utils/wml_fm_utils.py
ibm_wos_utils/__init__.py
ibm_wos_utils/common/__init__.py
ibm_wos_utils/common/activity_tracking/__init__.py
ibm_wos_utils/common/activity_tracking/activity_tracker.py
ibm_wos_utils/common/activity_tracking/activity_tracker_utils.py
ibm_wos_utils/common/batch/__init__.py
ibm_wos_utils/common/batch/jobs/__init__.py
ibm_wos_utils/common/batch/jobs/configuration.py
ibm_wos_utils/common/batch/jobs/create_remote_table_job.py
ibm_wos_utils/common/batch/jobs/simplified_configuration.py
ibm_wos_utils/common/batch/jobs/validate_table.py
ibm_wos_utils/common/batch/utils/__init__.py
ibm_wos_utils/common/batch/utils/configuration_generator.py
ibm_wos_utils/common/batch/utils/configuration_utility.py
ibm_wos_utils-5.3.0.10.dist-info/LICENSE
ibm_wos_utils-5.3.0.10.dist-info/METADATA
ibm_wos_utils-5.3.0.10.dist-info/WHEEL
ibm_wos_utils-5.3.0.10.dist-info/top_level.txt
ibm_wos_utils-5.3.0.10.dist-info/RECORD
