Metadata-Version: 2.1
Name: ibm_wos_utils
Version: 5.3.0.10
Summary: IBM Watson OpenScale API client utility module
Home-page: https://dataplatform.cloud.ibm.com/docs/content/wsj/model/getting-started.html?audience=wdp
Author: IBM
Author-email: pvemulam@in.ibm.com, venkataramana.m@in.ibm.com
License: Apache 2.0
Keywords: OpenScale,Watson,IBM,IBM Cloud,CPD,IBM Cloud Pak for Data
Classifier: Development Status :: 5 - Production/Stable
Classifier: Natural Language :: English
Classifier: License :: OSI Approved :: Apache Software License
Classifier: Programming Language :: Python :: 3.10
Classifier: Programming Language :: Python :: 3.11
Classifier: Operating System :: MacOS :: MacOS X
Classifier: Operating System :: POSIX :: Linux
Classifier: Intended Audience :: Science/Research
Classifier: Intended Audience :: Developers
Classifier: Intended Audience :: Information Technology
Classifier: Topic :: Software Development :: Libraries
Classifier: Topic :: Software Development :: Libraries :: Python Modules
Classifier: Topic :: Scientific/Engineering :: Artificial Intelligence
Classifier: Topic :: Scientific/Engineering :: Information Analysis
Classifier: Topic :: Internet
Requires-Python: >=3.10,<3.14
License-File: LICENSE
Requires-Dist: numpy <3.0.0,>=2.0.0
Requires-Dist: scipy ~=1.15.2
Requires-Dist: pandas <2.3.0,>=2.2.0
Requires-Dist: scikit-learn ==1.6.1
Requires-Dist: scikit-image ~=0.25.0
Requires-Dist: imageio ~=2.37.0
Requires-Dist: requests <3.0,>=2.31.0
Requires-Dist: tqdm ~=4.66.1
Requires-Dist: jenkspy ~=0.4.0
Requires-Dist: more-itertools ~=10.2.0
Requires-Dist: retrying ~=1.3.4
Requires-Dist: boto3 ~=1.37.30
Requires-Dist: PyJWT ~=2.10.0
Requires-Dist: cachetools ~=5.3.3
Requires-Dist: aiohttp <4.0.0,>=3.12.14
Requires-Dist: urllib3 ~=2.5.0
Requires-Dist: aiohttp-retry <3.0.0,>=2.9.1
Provides-Extra: cos
Requires-Dist: ibm-cos-sdk ~=2.14.0 ; extra == 'cos'
Requires-Dist: ibm-cos-sdk-core ~=2.14.0 ; extra == 'cos'
Provides-Extra: database
Requires-Dist: ibm-db <3.2.7,>=3.2.3 ; extra == 'database'
Requires-Dist: psycopg2 ~=2.9.9 ; extra == 'database'
Requires-Dist: redis[hiredis] ~=5.2.0 ; extra == 'database'
